setup.py
dictman/DBManagers.py
dictman/Managers.py
dictman/Spider.py
dictman/__init__.py
dictman/main.py
dictman.egg-info/PKG-INFO
dictman.egg-info/SOURCES.txt
dictman.egg-info/dependency_links.txt
dictman.egg-info/entry_points.txt
dictman.egg-info/requires.txt
dictman.egg-info/top_level.txt