Metadata-Version: 1.0
Name: dictman
Version: 0.1.3
Summary: a English word shell finder
Home-page: UNKNOWN
Author: zhanglun
Author-email: zhanglun.me@gmail.com
License: UNKNOWN
Platform: UNKNOWN
